alembic/__init__.py
alembic/__main__.py
alembic/command.py
alembic/config.py
alembic/context.py
alembic/context.pyi
alembic/environment.py
alembic/migration.py
alembic/op.py
alembic/op.pyi
alembic/py.typed
alembic/autogenerate/__init__.py
alembic/autogenerate/api.py
alembic/autogenerate/compare.py
alembic/autogenerate/render.py
alembic/autogenerate/rewriter.py
alembic/ddl/__init__.py
alembic/ddl/base.py
alembic/ddl/impl.py
alembic/ddl/mssql.py
alembic/ddl/mysql.py
alembic/ddl/oracle.py
alembic/ddl/postgresql.py
alembic/ddl/sqlite.py
alembic/operations/__init__.py
alembic/operations/base.py
alembic/operations/batch.py
alembic/operations/ops.py
alembic/operations/schemaobj.py
alembic/operations/toimpl.py
alembic/runtime/__init__.py
alembic/runtime/environment.py
alembic/runtime/migration.py
alembic/script/__init__.py
alembic/script/base.py
alembic/script/revision.py
alembic/script/write_hooks.py
alembic/templates/async/README
alembic/templates/async/alembic.ini.mako
alembic/templates/async/env.py
alembic/templates/async/script.py.mako
alembic/templates/generic/README
alembic/templates/generic/alembic.ini.mako
alembic/templates/generic/env.py
alembic/templates/generic/script.py.mako
alembic/templates/multidb/README
alembic/templates/multidb/alembic.ini.mako
alembic/templates/multidb/env.py
alembic/templates/multidb/script.py.mako
alembic/testing/__init__.py
alembic/testing/assertions.py
alembic/testing/env.py
alembic/testing/fixtures.py
alembic/testing/requirements.py
alembic/testing/schemacompare.py
alembic/testing/util.py
alembic/testing/warnings.py
alembic/testing/plugin/__init__.py
alembic/testing/plugin/bootstrap.py
alembic/testing/suite/__init__.py
alembic/testing/suite/_autogen_fixtures.py
alembic/testing/suite/test_autogen_comments.py
alembic/testing/suite/test_autogen_computed.py
alembic/testing/suite/test_autogen_diffs.py
alembic/testing/suite/test_autogen_fks.py
alembic/testing/suite/test_autogen_identity.py
alembic/testing/suite/test_environment.py
lolopinto_alembic_fork-0.0.1.dev0.dist-info/LICENSE
lolopinto_alembic_fork-0.0.1.dev0.dist-info/METADATA
lolopinto_alembic_fork-0.0.1.dev0.dist-info/WHEEL
lolopinto_alembic_fork-0.0.1.dev0.dist-info/entry_points.txt
lolopinto_alembic_fork-0.0.1.dev0.dist-info/top_level.txt
lolopinto_alembic_fork-0.0.1.dev0.dist-info/RECORD
