Metadata-Version: 2.1
Name: lolopinto-alembic-fork
Version: 0.0.1.dev0
Summary: A database migration tool for SQLAlchemy.
Home-page: https://alembic.sqlalchemy.org
Author: Mike Bayer
Author-email: mike_mp@zzzcomputing.com
License: MIT
Project-URL: Source, https://github.com/sqlalchemy/alembic/
Project-URL: Documentation, https://alembic.sqlalchemy.org/en/latest/
Project-URL: Issue Tracker, https://github.com/sqlalchemy/alembic/issues/
Classifier: Development Status :: 5 - Production/Stable
Classifier: Intended Audience :: Developers
Classifier: Environment :: Console
Classifier: License :: OSI Approved :: MIT License
Classifier: Operating System :: OS Independent
Classifier: Programming Language :: Python
Classifier: Programming Language :: Python :: 3
Classifier: Programming Language :: Python :: 3.7
Classifier: Programming Language :: Python :: 3.8
Classifier: Programming Language :: Python :: 3.9
Classifier: Programming Language :: Python :: 3.10
Classifier: Programming Language :: Python :: Implementation :: CPython
Classifier: Programming Language :: Python :: Implementation :: PyPy
Classifier: Topic :: Database :: Front-Ends
Requires-Python: >=3.7
License-File: LICENSE
Requires-Dist: SQLAlchemy >=1.3.0
Requires-Dist: Mako
Requires-Dist: typing-extensions >=4
Requires-Dist: importlib-metadata ; python_version < "3.9"
Requires-Dist: importlib-resources ; python_version < "3.9"
Provides-Extra: tz
Requires-Dist: python-dateutil ; extra == 'tz'
